odoo/addons/website_sale_hide_empty_category/README.rst
odoo/addons/website_sale_hide_empty_category/__init__.py
odoo/addons/website_sale_hide_empty_category/__manifest__.py
odoo/addons/website_sale_hide_empty_category/i18n/es.po
odoo/addons/website_sale_hide_empty_category/i18n/website_sale_hide_empty_category.pot
odoo/addons/website_sale_hide_empty_category/models/__init__.py
odoo/addons/website_sale_hide_empty_category/models/product_public_category.py
odoo/addons/website_sale_hide_empty_category/readme/CONTRIBUTORS.rst
odoo/addons/website_sale_hide_empty_category/readme/DESCRIPTION.rst
odoo/addons/website_sale_hide_empty_category/readme/USAGE.rst
odoo/addons/website_sale_hide_empty_category/static/description/icon.png
odoo/addons/website_sale_hide_empty_category/static/description/index.html
odoo/addons/website_sale_hide_empty_category/static/src/js/tour.js
odoo/addons/website_sale_hide_empty_category/tests/__init__.py
odoo/addons/website_sale_hide_empty_category/tests/test_has_product_recursive.py
odoo/addons/website_sale_hide_empty_category/tests/test_ui.py
odoo/addons/website_sale_hide_empty_category/views/assets.xml
odoo/addons/website_sale_hide_empty_category/views/website_sale_templates.xml
odoo13_addon_website_sale_hide_empty_category-13.0.1.1.0.dist-info/METADATA
odoo13_addon_website_sale_hide_empty_category-13.0.1.1.0.dist-info/WHEEL
odoo13_addon_website_sale_hide_empty_category-13.0.1.1.0.dist-info/top_level.txt
odoo13_addon_website_sale_hide_empty_category-13.0.1.1.0.dist-info/RECORD
